{
  "Адрес доставки": "Адрес доставки",
  "Войти": "Войти",
  "Выход": "Выход",
  "Заказ добавлен в корзину": "Заказ добавлен в корзину",
  "Заказ успешно сформирован": "Заказ успешно сформирован",
  "Заказать": "Заказать",
  "Заказы": "Заказы",
  "Имя": "Имя",
  "Карта": "Карта",
  "Корзина пуста": "Корзина пуста",
  "Купить": "Купить",
  "Меню": "Меню",
  "На странице возникла ошибка": "На странице возникла ошибка",
  "Наличные": "Наличные",
  "Ошибка авторизации": "Ошибка авторизации",
  "Ошибка на стороне сервера": "Ошибка на стороне сервера",
  "Почта": "Почта",
  "Русский": "Русский",
  "Сумма": "Сумма",
  "Такой страницы не существует": "Такой страницы не существует"
}
